vidtoolz_intro/__init__.py
vidtoolz_intro-0.1.1.dist-info/licenses/LICENSE
vidtoolz_intro-0.1.1.dist-info/METADATA
vidtoolz_intro-0.1.1.dist-info/WHEEL
vidtoolz_intro-0.1.1.dist-info/entry_points.txt
vidtoolz_intro-0.1.1.dist-info/top_level.txt
vidtoolz_intro-0.1.1.dist-info/RECORD
