Metadata-Version: 2.4
Name: vidtoolz-intro
Version: 0.1.1
Summary: Create intro video from a series of videos
Author: Sukhbinder Singh
License: Apache-2.0
Project-URL: Homepage, https://github.com/sukhbinder/vidtoolz-intro
Project-URL: Changelog, https://github.com/sukhbinder/vidtoolz-intro/releases
Project-URL: Issues, https://github.com/sukhbinder/vidtoolz-intro/issues
Project-URL: CI, https://github.com/sukhbinder/vidtoolz-intro/actions
Classifier: License :: OSI Approved :: Apache Software License
License-File: LICENSE
Requires-Dist: vidtoolz
Requires-Dist: vidtoolz-concat
Requires-Dist: vidtoolz-trim
Provides-Extra: test
Requires-Dist: pytest; extra == "test"
Dynamic: license-file
